pimkl/__init__.py
pimkl/analysis.py
pimkl/data.py
pimkl/evaluation.py
pimkl/inducers.py
pimkl/network.py
pimkl/pimkl.py
pimkl/run.py
pimkl/cli/__init__.py
pimkl/cli/analyse.py
pimkl/cli/cli.py
pimkl/cli/preprocess.py
pimkl/factories/__init__.py
pimkl/factories/estimator_factory.py
pimkl/factories/induction_factory.py
pimkl/factories/mkl_factory.py
pimkl/models/__init__.py
pimkl/models/pimkl.py
pimkl/utils/__init__.py
pimkl/utils/objects.py
pimkl/utils/preprocessing/__init__.py
pimkl/utils/preprocessing/core.py
pimkl/utils/preprocessing/scaler.py
pimkl/utils/preprocessing/standardizer.py
pimkl-0.1.1.dist-info/AUTHORS.rst
pimkl-0.1.1.dist-info/LICENSE
pimkl-0.1.1.dist-info/METADATA
pimkl-0.1.1.dist-info/WHEEL
pimkl-0.1.1.dist-info/entry_points.txt
pimkl-0.1.1.dist-info/top_level.txt
pimkl-0.1.1.dist-info/RECORD
