Metadata-Version: 2.1
Name: pimkl
Version: 0.1.1
Summary: pathway induced multiple kernel learning for computational biology
Home-page: https://github.com/PhosphorylatedRabbits/pimkl
Author: Joris Cadow and Matteo Manica
Author-email: joriscadow@gmail.com, drugilsberg@gmail.com
License: MIT license
Keywords: pimkl
Platform: UNKNOWN
Classifier: Development Status :: 2 - Pre-Alpha
Classifier: Intended Audience :: Developers
Classifier: License :: OSI Approved :: MIT License
Classifier: Natural Language :: English
Classifier: Programming Language :: Python :: 3
Classifier: Programming Language :: Python :: 3.5
Classifier: Programming Language :: Python :: 3.6
Classifier: Programming Language :: Python :: 3.7
Requires-Python: >=3.5
Requires-Dist: numpy (>=1.14.0)
Requires-Dist: scipy (>=1.0.0)
Requires-Dist: pandas (>=0.22.0)
Requires-Dist: scikit-learn (>=0.18.1)
Requires-Dist: networkx (>=2.1)
Requires-Dist: statsmodels (>=0.8.0)
Requires-Dist: seaborn (>=0.8.1)
Requires-Dist: Click (>=7.0)
Requires-Dist: tqdm (>=4.36.1)
